{"type":"PR","pr":{"number":51,"head":"96ca7f0a93794b0236ecf309ccb59c1687e71e86"},"user":"Heyhoe","status":"pending_publish","branch":"cms/eigenvectors-from-eigenvalues-を-julia-で検証する","collection":"posts","title":"Eigenvectors from Eigenvalues を Julia で検証する","description":"Twitter で話題になったり研究室の slack で話されたりしていたので Julia で書いてみた  \n - Eigenvectors from Eigenvalues  \n - Peter B. Denton, Stephen J. Parke, Terence Tao, Xining Zhang","objects":{"entry":{"path":"content/posts/eigenvectors-from-eigenvalues-を-julia-で検証する.md","sha":"808b106134eda11df8910e0f273d008dd9ce5d40"},"files":[]},"timeStamp":"2019-11-19T08:47:09.564Z"}