{"type":"PR","pr":{"number":48,"head":"dabcf02785bb90b1f67a5968d8c40bc2f7d22aa9"},"user":"Heyhoe","status":"pending_publish","branch":"cms/webpack-typescript-three-js-で-glsl-frag-vert-を外部モジュールとして-import-する","collection":"posts","title":"webpack + typescript + three.js で GLSL (.frag|.vert) を外部モジュールとして import する","description":"typescript + three.js で GLSL をいい感じに編集したい","objects":{"entry":{"path":"content/posts/webpack-typescript-three-js-で-glsl-frag-vert-を外部モジュールとして-import-する.md","sha":"7e129665ed73c69fccc16373b806550ccb294638"},"files":[]},"timeStamp":"2019-11-14T20:52:51.876Z"}