{"type":"PR","pr":{"number":42,"head":"ab79f0bc589c9e598709b9f0d221ce78448746b7"},"user":"Heyhoe","status":"draft","branch":"cms/論文読み-how-do-humans-sketch-objects","collection":"posts","title":"[論文読み] How Do Humans Sketch Objects? ","description":"人間はどのように物体をスケッチするか","objects":{"entry":{"path":"content/posts/論文読み-how-do-humans-sketch-objects.md","sha":"206f482689ddbf611171ff0d5b03a16b057ab5ff"},"files":[{"path":"/static/img/uploads/スクリーンショット-2019-10-24-17.06.36.png","sha":"5351ff387ef71e052800f603dc3dc7342d68f341"}]},"timeStamp":"2019-10-24T08:09:50.865Z"}